ccda_to_omop/README.md
ccda_to_omop/__init__.py
ccda_to_omop/__init__.py~
ccda_to_omop/code_hunt.py
ccda_to_omop/data_driven_parse.py
ccda_to_omop/data_driven_parse.py~
ccda_to_omop/ddl.py
ccda_to_omop/domain_dataframe_column_types.py
ccda_to_omop/find_paths.py
ccda_to_omop/layer_datasets.py
ccda_to_omop/layer_datasets.py~
ccda_to_omop/spark_dataframe_column_types.py
ccda_to_omop/spark_dataframe_column_types.py~
ccda_to_omop/test_find_paths.txt
ccda_to_omop/util.py
ccda_to_omop/value_transformations.py
ccda_to_omop/value_transformations.py~
ccda_to_omop/metadata/__init__.py
ccda_to_omop/metadata/care_site_ee_hcf.py
ccda_to_omop/metadata/care_site_ee_hcf_location.py
ccda_to_omop/metadata/care_site_pr.py
ccda_to_omop/metadata/care_site_pr_location.py
ccda_to_omop/metadata/condition.py
ccda_to_omop/metadata/device_organizer_procedure.py
ccda_to_omop/metadata/device_organizer_supply.py
ccda_to_omop/metadata/device_procedure.py
ccda_to_omop/metadata/device_supply.py
ccda_to_omop/metadata/immunization_immunization_activity.py
ccda_to_omop/metadata/location.py
ccda_to_omop/metadata/measurement.py
ccda_to_omop/metadata/measurement_vital_signs.py
ccda_to_omop/metadata/medication_medication_activity.py
ccda_to_omop/metadata/medication_medication_dispense.py
ccda_to_omop/metadata/observation.py
ccda_to_omop/metadata/observation_social_history_cultural.py
ccda_to_omop/metadata/observation_social_history_home_environment.py
ccda_to_omop/metadata/observation_social_history_pregnancy.py
ccda_to_omop/metadata/observation_social_history_smoking.py
ccda_to_omop/metadata/observation_social_history_tobacco_use.py
ccda_to_omop/metadata/person.py
ccda_to_omop/metadata/procedure_activity_act.py
ccda_to_omop/metadata/procedure_activity_act_measurement.py
ccda_to_omop/metadata/procedure_activity_act_observation.py
ccda_to_omop/metadata/procedure_activity_observation.py
ccda_to_omop/metadata/procedure_activity_procedure.py
ccda_to_omop/metadata/procedure_activity_procedure.py~
ccda_to_omop-0.0.20.dist-info/METADATA
ccda_to_omop-0.0.20.dist-info/WHEEL
ccda_to_omop-0.0.20.dist-info/licenses/LICENSE
ccda_to_omop-0.0.20.dist-info/RECORD
