Metadata-Version: 2.4
Name: ccda_to_omop
Version: 0.0.20
Summary: A package for converting HL7 CCDA documents to OHDSI OMOP
Project-URL: Homepage, https://github.com/cladteam/CCDA_OMOP_Conversion_Package
Project-URL: Issues, https://github.com/cladteam/CCDA_OMOP_by_Python/issues
Author-email: Chris Roeder <chris@tislab.org>, Chris Roeder <roederc@unc.med.edu>
License-Expression: GPL-3.0
License-File: LICENSE
Classifier: Operating System :: OS Independent
Classifier: Programming Language :: Python :: 3
Requires-Python: >=3.10
Requires-Dist: duckdb>=1.3.0
Requires-Dist: logging==0.4.9.6
Requires-Dist: lxml==5.4.0
Requires-Dist: numpy==2.2.6
Requires-Dist: pandas==2.2.3
Requires-Dist: python-dateutil==2.9.0
Requires-Dist: pytz==2025.2
Requires-Dist: requests==2.32.3
Requires-Dist: setuptools==80.9.0
Requires-Dist: typeguard==4.4.3
